psygen/__init__.py
psygen/agent_model.py
psygen/prompt.txt
psygen/.ipynb_checkpoints/prompt-checkpoint.txt
psygen/trait/__init__.py
psygen/trait/adaptation.py
psygen/trait/cognitive_creative.py
psygen/trait/emotional_stability.py
psygen/trait/human_abstract_profile.py
psygen/trait/human_emergent_trait_profile.py
psygen/trait/moral_normative.py
psygen/trait/self_appraisal.py
psygen/trait/self_governance.py
psygen/trait/social_relational.py
psygen/trait/utils/__init__.py
psygen/trait/utils/probability_helpers.py
psygen-0.1.1.dist-info/licenses/LICENSE.md
psygen-0.1.1.dist-info/METADATA
psygen-0.1.1.dist-info/WHEEL
psygen-0.1.1.dist-info/top_level.txt
psygen-0.1.1.dist-info/RECORD
