Metadata-Version: 2.4
Name: psygen
Version: 0.1.1
Summary: Randomly generate human psychological traits for realistic human behavior
Author: Anh Phan Nguyen
License: MIT License
Requires-Python: >=3.10
License-File: LICENSE.md
Requires-Dist: numpy
Dynamic: license-file
